Workbook

Sheet ordinary普货
A1: Weifang Yipin Pet Articles Co.,Ltd
A2: ADD: R 301Q, Building 1, Shengshi Haoting Huijingyuan, No. 1999 Wenhua Road, Kuiwen District, Weifang City, Shandong Province,China
A3: yeeaquarium@chongujia.com
A4: INVOICE
A5: Customer Info | G5: Order Info
A6: EXW 客户唛头：Umg Hussein Bassem /Jaafar 07716666543 仓库地址:广东省佛山市南海区里水胜利五一村电台路北3号(自编:8座101) 联系方式:13202011126，李先生 / 136 68976856, Musa 收货时间:周一至周六10:00-18:00 | G6: Invoice No.: 202601050235 Invoice Date: 2026-01-05 Sales Rep: Tina Tong
A7: ORDER 1 （ordinary goods）普货
A8: Item No. | B8: Picture | C8: Business Code | D8: Model | E8: Chinese Name | F8: English Name | G8: Price | H8: QTY | I8: Amount | J8: Remark
G9: （USD） | H9: (PCS) | I9: （USD）
A10: 1 | C10: 1.5.1.7 | D10: YEE-3006 | E10: 50W纯钢加热棒 YSH-50 | F10: 50W pure steel heating rod YSH-50 | G10: 2.4788732 | H10: 8 | I10: =G10*H10 -> 19.830986
A11: 2 | C11: 1.5.1.8 | D11: YEE-3007 | E11: 100W纯钢加热棒 YSH-100 | F11: 100W pure steel heating rod YSH-100 | G11: 2.5633803 | H11: 8 | I11: =G11*H11 -> 20.507042
A12: 3 | C12: 1.5.1.9 | D12: YEE-3008 | E12: 200W纯钢加热棒 YSH-200 | F12: 200W pure steel heating rod YSH-200 | G12: 2.5774648 | H12: 8 | I12: =G12*H12 -> 20.619718
A13: 4 | C13: C4-1432-1 | D13: C4-1432 | E13: Yee意牌水族皓源石英加热棒 100W | F13: Yee brand aquarium quartz heating rod, 100W | G13: 9.76 | H13: 1 | I13: =G13*H13 -> 9.76
A14: 5 | C14: C4-1103-4 | D14: C4-1103 | E14: YEE黑武士加热棒 100W | F14: YEE Black Warrior Heater 100W | G14: 3.5211268 | H14: 5 | I14: =G14*H14 -> 17.605634
A15: 6 | C15: 03326 | D15: YTZ-300 | E15: 小白单孔氧气泵3W（不可调）YTZ-300 | F15: Xiaobai single-hole oxygen pump 3W (non-adjustable) YTZ-300 | G15: 1.1690141 | H15: 3 | I15: 3.51
A16: 7 | C16: 07154 | D16: YGG-135 | E16: YEE 50mm 球形矿物质气泡扩散器 | F16: YEE 50mm Ball Mineral Bubble Diffuser | G16: 1.56 | H16: 15 | I16: 23.4
A17: 8 | C17: C5-1144-1a | D17: C5-1144 | E17: 加强版1.5米/加厚加长 | F17: Enhanced version 1.5 meters/thickened and lengthened | G17: 0.36619718 | H17: 10 | I17: 3.66
A18: 9 | C18: 1.8.3.2 | D18: YEE-3621 | E18: 【加厚气囊 经久耐用】1.7米 | F18: 【Thickened airbag for durability】1.7 meters | G18: 0.91549296 | H18: 10 | I18: 9.15
A19: 10 | C19: C4-1117-1 | D19: C4-1117 | E19: 高配30W 低水位 | F19: High configuration 30W low water level | G19: 8.2816901 | H19: 5 | I19: 41.41
A20: 11 | C20: C4-1008-1 | D20: C4-1008 | E20: 悬浮隔离盒大号 | F20: Large suspended isolation box | G20: 2.6760563 | H20: 8 | I20: 21.41
A21: 12 | C21: 02517 | D21: YSL-506 | E21: 大号气动孵化盒（双房） | F21: Large pneumatic incubator (double room) | G21: 0.99 | H21: 5 | I21: 4.95
A22: 13 | C22: 02771 | D22: YKL-018 | E22: 亚克力培养箱 20*10*10 | F22: Acrylic incubator 20*10*10 | G22: 2.86 | H22: 4 | I22: 11.44
A23: 14 | C23: 05617a | D23: YLL-087 | E23: （蓝色）新升级6D 过滤棉 50*40 两片装 | F23: (Blue) New upgraded 6D filter cotton 50*40 two pieces | G23: 3.0422535 | H23: 4 | I23: 12.17
A24: 15 | C24: 07116 | D24: YFF-042 | E24: 纳米培养环混合装 | F24: Nano Culture Ring Mixed Pack | G24: 1.31 | H24: 8 | I24: 10.48
A25: 16 | C25: 17699a | D25: YAA-009. | E25: 高能量培菌砖 | F25: High energy culture bricks | G25: 0.83 | H25: 5 | I25: 4.15
A26: 17 | C26: 11578 | D26: NYH-006 | E26: Nepall 3D曲奇滤材 500g | F26: 3D filter material | G26: 1.67 | H26: 6 | I26: 10.02
A27: 18 | C27: 71934 | D27: YLC-410 | E27: 十六合一滤材 2.5kg | F27: 16-in-1 filter material 2.5kg | G27: 2.6056338 | H27: 5 | I27: 13.03
A28: 19 | C28: 17831 | D28: YLC-409 | E28: 六合一滤材 500g | F28: Six-in-one filter material 500g | G28: 0.97183099 | H28: 5 | I28: 4.86
A29: 20 | C29: C4-1067-1 | D29: C4-1067 | E29: 3W 油膜处理器 | F29: 3W oil film processor | G29: 2.61 | H29: 4 | I29: 10.44
A30: 21 | C30: 08116 | D30: LED-318 | E30: yee三色可调 3.5W 双排广角灯27cm | F30: Yee three-color adjustable 3.5W double-row wide-angle light, 27cm | G30: 0 | H30: 4 | I30: 0 | J30: Free gift
A31: 22 | C31: 07140 | D31: CLS-107 | E31: 鱼缸磁力刷 大号 蓝色强磁 | F31: Aquarium magnetic cleaning brush, large size, blue, strong magnet. | G31: 0 | H31: 3 | I31: 0 | J31: Free gift
A32: 23 | C32: 1.15.60 | D32: YEE-3656 | E32: 16mm牛筋管1.0米 | F32: 1.0 meter of 16mm reinforced plastic tubing | G32: 0 | H32: 5 | I32: 0 | J32: Free gift
A33: 24 | C33: 06255 | D33: =VLOOKUP(C33,[1]水草缸!$A:$C,3,0) -> YXL-003 | E33: 400x230x250mm 5mm厚 | F33: 400x230x250mm 5mm thick | G33: 6.2816901 | H33: 2 | I33: =G33*H33 -> 12.56338 | J33: 打木箱，大小号嵌套，内部塞其它产品
A34: 25 | C34: 05380 | D34: =VLOOKUP(C34,[1]水草缸!$A:$C,3,0) -> YKK-50 | E34: 500x270x300mm 5mm厚 | F34: 500x270x300mm 5mm thick | G34: 9.7323944 | H34: 2 | I34: =G34*H34 -> 19.464789
A35: 26 | C35: 05381 | D35: =VLOOKUP(C35,[1]水草缸!$A:$C,3,0) -> YKK-60 | E35: 600x300x350mm 5mm厚 | F35: 600x300x350mm 5mm thick | G35: 12.521127 | H35: 2 | I35: =G35*H35 -> 25.042254
A36: 27 | C36: 16932 | D36: =VLOOKUP(C36,[1]水草缸!$A:$C,3,0) -> YEE-1090 | E36: 35×35×35 6mm 厚 | F36: 35×35×35 6mm thick | G36: 8.5915493 | H36: 2 | I36: =G36*H36 -> 17.183099 | J36: 打木箱，大小号嵌套，内部塞其它产品
A37: 28 | C37: 05662 | D37: =VLOOKUP(C37,[1]水草缸!$A:$C,3,0) -> YCG-40 | E37: 40X40X40cm 6mm厚 | F37: 40X40X40cm 6mm thick | G37: 11.549296 | H37: 2 | I37: =G37*H37 -> 23.098592
A38: 29 | C38: C5-1062-1 | D38: =VLOOKUP(C38,[1]水草缸!$A:$C,3,0) -> C5-1062 | E38: 60*40*40cm 8mm | F38: 60*40*40cm 8mm | G38: 18.169014 | H38: 2 | I38: =G38*H38 -> 36.338028 | J38: 打木箱，内部塞其它产品
A39: 30 | C39: C5-1123-2 | D39: C5-1123 | E39: 裸缸侧虑溪流缸60*15*15cm 6mm送水泵 | F39: Bare side stream tank 60*15*15cm 6mm water pump | G39: 17.295775 | H39: 2 | I39: =G39*H39 -> 34.591549 | J39: 打木箱，内部塞其它产品
A40: Products price | I40: =SUM(I10:I39) -> 440.68507
A41: Packaging fee | I41: 65
A42: ORDER 1 : Total price | I42: =I40+I41 -> 505.68507
A43: ORDER 2 （sensitive goods）敏货
A44: 1 | C44: C1-1113-2 | D44: C1-1113 | E44: Yee小型鱼配合饲料全效合一0.6mm75g | F44: Yee Small Fish Feed All-in-One 0.6mm 75g | G44: 0.63 | H44: 25 | I44: =G44*H44 -> 15.75
A45: 2 | C45: C1-1127-1 | D45: C1-1127 | E45: 金鱼兰寿善玉菌+螺旋藻色扬配合饲料290g缓沉3.0mm | F45: Goldfish Orchid Longevity Jade Fungus + Spirulina Color Yang Compound Feed 290g Slow Sinking 3.0mm | G45: 1.8 | H45: 15 | I45: =G45*H45 -> 27
A46: 3 | C46: C1-1073-1a | D46: C1-1073 | E46: Yee斗鱼配合饲料0.8mm130g新更换条码 | F46: Betta fish food 0.8mm 130g New | G46: 0.97 | H46: 20 | I46: =G46*H46 -> 19.4
A47: 4 | C47: C1-1082-5 | D47: C1-1082 | E47: 仿红虫0.5mm115gLLG | F47: Imitation red worm feed 0.5mm 115g | G47: 1.35 | H47: 30 | I47: =G47*H47 -> 40.5
A48: 5 | C48: C1-1065-1 | D48: C1-1065 | E48: Yee蝴蝶鲤配合饲料1.5mm300g袋装 | F48: Floating Grain - Competition Grade 45% High Protein [1.5mm Small Particles] 300g Bag | G48: 0.86 | H48: 1 | I48: =G48*H48 -> 0.86
A49: 6 | C49: C1-1066-2 | D49: C1-1066 | E49: Yee水族观赏虾专用粮260g | F49: 【40% High Protein】Special Food for Ornamental Shrimp 260g | G49: 1.7 | H49: 1 | I49: =G49*H49 -> 1.7
A50: 7 | C50: 03446a | D50: YYY-078 | E50: 新款脱壳卵(80g150ml)白瓶+喂食器SJ | F50: New Shelled Eggs (80g 150ml) White Bottle + Feeder | G50: 1.65 | H50: 10 | I50: =G50*H50 -> 16.5
A51: 8 | C51: C1-1125-1 | D51: C1-1125 | E51: Yee水族-寄居蟹冻干盛宴55g55g | F51: Yee Aqua-Hermit Crab Freeze-Dried Feast 55g | G51: 1.27 | H51: 1 | I51: =G51*H51 -> 1.27
A52: 10 | C52: C1-1082-2a | D52: C1-1082 | E52: Yee小型鱼配合饲料全效合一0.2mm210g更换条码 | F52: 【All-in-one】Microparticles/0.2mm/210g | G52: 1.04 | H52: 10 | I52: =G52*H52 -> 10.4
A53: 11 | C53: C1-1134-6 | D53: C1-1134 | E53: 金鱼兰寿配合饲料1.5mm下沉500g袋装 | F53: Ranchu goldfish formulated feed, 1.5mm diameter, sinks 500g per bag. | G53: 1.69 | H53: 12 | I53: =G53*H53 -> 20.28
A54: 12 | C54: C1-1086-1 | D54: C1-1086 | E54: Yee水族冻干丰年虾块18g | F54: Yee Aquarium Freeze-dried Brine Shrimp Chunks 18g 225ml | G54: 0.9 | H54: 8 | I54: =G54*H54 -> 7.2
A55: 13 | C55: C1-1124-1 | D55: C1-1124 | E55: Yee意牌水族三合一斗鱼配合饲料15g | F55: Yee Brand 3-in-1 Betta Fish Food 15g | G55: 0.48 | H55: 10 | I55: =G55*H55 -> 4.8
A56: 14 | C56: 12420 | D56: YYH-125 | E56: 白点净300ml | F56: White Spot Cleaner 300ml | G56: 0.71830986 | H56: 10 | I56: =G56*H56 -> 7.1830986
A57: 15 | C57: 19768a | D57: YYH-207 | E57: 亚甲基蓝溶液 600ml | F57: Methylene blue solution 600ml | G57: 0.93 | H57: 8 | I57: =G57*H57 -> 7.44
A58: 16 | C58: 02856a | D58: YYH-006 | E58: 杀菌/抑菌/速溶粉末2g/袋×10袋[1盒] | F58: Bactericidal/antibacterial/instant powder 2g/bag × 10 bags [1 box] | G58: 1.13 | H58: 6 | I58: =G58*H58 -> 6.78
A59: 17 | C59: c2-1016-2 | D59: c2-1016 | E59: Yee意牌水族净氨系列活性益生菌760ml | F59: Yee Aquarium Cleansing Ammonia Series Active Probiotics 760ml | G59: 2.34 | H59: 10 | I59: =G59*H59 -> 23.4
A60: 18 | C60: c2-1016-1a | D60: c2-1016 | E60: Yee意牌水族净氨系列活性益生菌400ml | F60: Yee Aquarium Cleansing Ammonia Series Active Probiotics 400ml | G60: 1.38 | H60: 5 | I60: =G60*H60 -> 6.9
A61: 19 | C61: 02924 | D61: YYH-039 | E61: yee蓝色经典-除氯水质稳定剂535ml | F61: Yee Blue Classic-Chlorine Removal Water Stabilizer 535ml | G61: 0.72 | H61: 15 | I61: =G61*H61 -> 10.8
A62: 20 | C62: 16940 | D62: YYH-173 | E62: 抗应激水质稳定剂 500ml 新风格 | F62: Anti-stress water stabilizer 500ml New style | G62: 0.91549296 | H62: 8 | I62: =G62*H62 -> 7.3239437
A63: 21 | C63: C3-1010-3 | D63: C3-1010 | E63: 【氨氮测试剂】可测约60次/精准快速 | F63: 【Ammonia nitrogen tester】can test about 60 times/accurate and fast | G63: 2.87 | H63: 8 | I63: =G63*H63 -> 22.96
A64: 22 | C64: C3-1010-1 | D64: C3-1010 | E64: 【亚硝酸盐测试剂】可测约100次/精准快速 | F64: 【Nitrite test kit】can test about 100 times/accurate and fast | G64: 2.87 | H64: 8 | I64: =G64*H64 -> 22.96
A65: 23 | C65: C4-1123-1a | D65: C4-1123 | E65: 【新手级50条】9合1/桶装/带对比表 | F65: [Novice Level 50] 9-in-1/Bucket/With Comparison Chart | G65: 1.62 | H65: 10 | I65: =G65*H65 -> 16.2
A66: 24 | C66: C2-1005-1 | D66: C2-1005 | E66: Yee意牌水族硝化菌+益生菌胶囊50粒 | F66: Yee Aquarium Nitrifying Bacteria + Probiotics Capsules 50 capsules | G66: 0.85 | H66: 12 | I66: =G66*H66 -> 10.2
A67: 25 | C67: C2-1005-2 | D67: C2-1005 | E67: Yee意牌水族硝化菌+益生菌胶囊100粒 | F67: Yee Aquarium Nitrifying Bacteria + Probiotics Capsules 100 Capsules | G67: 1.27 | H67: 8 | I67: =G67*H67 -> 10.16
A68: 26 | C68: 19429 | D68: YYH-189 | E68: 除藻剂 500ml 新风格 | F68: Algaecide 500ml New Style | G68: 0.91549296 | H68: 10 | I68: =G68*H68 -> 9.1549296
A69: 27 | C69: 19939 | D69: YYH-216 | E69: 抗应激水质稳定剂 1000ml 新风格 | F69: Anti-stress water stabilizer 1000ml New style | G69: 1.1267606 | H69: 6 | I69: =G69*H69 -> 6.7605634
A70: 28 | C70: 06834 | D70: YAN-804 | E70: 多维矿物盐500克 | F70: Multivitamin mineral salt 500g | G70: 0.2 | H70: 10 | I70: =G70*H70 -> 2
A71: 29 | C71: 01831 | D71: YAN-915 | E71: 500G多维盐盒装YAN-915 | F71: 500G Multivitamin Salt Box YAN-915 | G71: 0.87 | H71: 5 | I71: =G71*H71 -> 4.35
A72: 30 | C72: 02938a | D72: YYH-053 | E72: yee蓝色经典-亚甲基蓝溶液235ml | F72: Yee Blue Classic-Methylene Blue Solution 235ml | G72: 0.45 | H72: 10 | I72: =G72*H72 -> 4.5
A73: 31 | C73: C4-1123-2a | D73: C4-1123 | E73: 【补充装】9合1/补充装/50条 | F73: 【Refill】9 in 1/Refill/50 pieces | G73: 1.06 | H73: 10 | I73: =G73*H73 -> 10.6
A74: 37 | C74: 07509 | D74: YFF-049 | E74: 水草泥肥力升级款细粒 1.5L | F74: Water grass mud fertility upgrade fine grain 1.5L | G74: 1.23 | H74: 18 | I74: =G74*H74 -> 22.14
A75: 38 | C75: 07512 | D75: YFF-052 | E75: 水草泥肥力升级款 粗粒 3L | F75: Water grass mud fertility upgrade coarse grain 3L | G75: 2.39 | H75: 10 | I75: =G75*H75 -> 23.9
A76: 48 | C76: 13343 | D76: PYD-200 | E76: 鱼缸除垢剂 200ml | F76: Fish tank descaling agent 200ml | G76: 0.76056338 | H76: 10 | I76: =G76*H76 -> 7.6056338
A77: 55 | C77: 00340 | D77: YEE-3606 | E77: 外贴电子温度计 | F77: External electronic thermometer | G77: 1.1 | H77: 4 | I77: 4.4 | J77: 装货单备注有电池
A78: Products price | I78: =SUM(I44:I77) -> 413.37817
A79: ORDER 2 : Total price | I79: =I78 -> 413.37817
A80: Total Freight fee | I80: 58
B81: Final payment for total order | I81: =I79+I42+I80 -> 977.06324
A82: Payment Term：100% payment before Delivery
