Workbook

Sheet Sheet1
A1: Weifang Yipin Pet Articles Co.,Ltd
A2: ADD: R 301Q, Building 1, Shengshi Haoting Huijingyuan, No. 1999 Wenhua Road, Kuiwen District, Weifang City, Shandong Province,China
A3: yeeaquarium@chongujia.com
A4: INVOICE
A5: Pickup Info | G5: Order Info
A6: EXW 客户自提 收货地址add：山东省潍坊市坊子区北海路翠坊街交叉口西行1000米汉唐电动汽车西门进 预估体积（Estimated total volume）: 1.5 cbm 预估重量（Estimated total weight）: 440 kg | G6: Invoice No.: 2512271150 Invoice Date: 2025-12-29 Sales Rep: Tina Tong
C7: Shipping Term: | F7: PI NO.:
A8: Item No. | B8: Picture | C8: Business Code | D8: Model | E8: Chinese Name | F8: English Name | G8: Price | H8: QTY | I8: Amount | J8: Remark
G9: （USD） | H9: (PCS) | I9: （USD）
A10: 1 | C10: C1-1113-2 | D10: C1-1113 | E10: Yee小型鱼配合饲料全效合一0.6mm75g | F10: Yee Small Fish Feed All-in-One 0.6mm 75g | G10: 0.63 | H10: 25 | I10: 15.75
A11: 2 | C11: C1-1127-1 | D11: C1-1127 | E11: 金鱼兰寿善玉菌+螺旋藻色扬配合饲料290g缓沉3.0mm | F11: Goldfish Orchid Longevity Jade Fungus + Spirulina Color Yang Compound Feed 290g Slow Sinking 3.0mm | G11: 1.8 | H11: 15 | I11: 27
A12: 3 | C12: C1-1073-1a | D12: C1-1073 | E12: Yee斗鱼配合饲料0.8mm130g新更换条码 | F12: Betta fish food 0.8mm 130g New | G12: 0.97 | H12: 20 | I12: 19.4
A13: 4 | C13: C1-1082-5 | D13: C1-1082 | E13: Imitation red worm feed 0.5mm 115g | F13: Imitation red worm feed 0.5mm 115g | G13: 1.35 | H13: 30 | I13: 40.5
A14: 5 | C14: C1-1065-1 | D14: C1-1065 | E14: Yee蝴蝶鲤配合饲料1.5mm300g袋装 | F14: Floating Grain - Competition Grade 45% High Protein [1.5mm Small Particles] 300g Bag | G14: 0.86 | H14: 1 | I14: 0.86
A15: 6 | C15: C1-1066-2 | D15: C1-1066 | E15: Yee水族观赏虾专用粮260g | F15: 【40% High Protein】Special Food for Ornamental Shrimp 260g | G15: 1.7 | H15: 1 | I15: 1.7
A16: 7 | C16: 03446a | D16: YYY-078 | E16: 新款脱壳卵(80g150ml)白瓶+喂食器SJ | F16: New Shelled Eggs (80g 150ml) White Bottle + Feeder | G16: 1.65 | H16: 1 | I16: 1.65
A17: 8 | C17: C1-1125-1 | D17: C1-1125 | E17: Yee水族-寄居蟹冻干盛宴55g55g | F17: Yee Aqua-Hermit Crab Freeze-Dried Feast 55g | G17: 1.27 | H17: 1 | I17: 1.27
A18: 9 | C18: C1-1069-1 | D18: C1-1069 | E18: 鱼粮连包铜版纸吊卡DJ | F18: Fish feed with coated paper hanger | G18: 0.62 | H18: 15 | I18: 9.3
A19: 10 | C19: C1-1082-2a | D19: C1-1082 | E19: Yee小型鱼配合饲料全效合一0.2mm210g更换条码 | F19: 【All-in-one】Microparticles/0.2mm/210g | G19: 1.04 | H19: 10 | I19: 10.4
A20: 11 | C20: C1-1134-6 | D20: C1-1134 | E20: 金鱼兰寿配合饲料1.5mm下沉500g袋装 | F20: Ranchu goldfish formulated feed, 1.5mm diameter, sinks 500g per bag. | G20: 1.69 | H20: 12 | I20: 20.28
A21: 12 | C21: C1-1086-1 | D21: C1-1086 | E21: Yee水族冻干丰年虾块18g | F21: Yee Aquarium Freeze-dried Brine Shrimp Chunks 18g 225ml | G21: 0.9 | H21: 8 | I21: 7.2
A22: 13 | C22: C1-1124-1 | D22: C1-1124 | E22: Yee意牌水族三合一斗鱼配合饲料15g | F22: Yee Brand 3-in-1 Betta Fish Food 15g | G22: 0.48 | H22: 10 | I22: 4.8
A23: 14 | C23: 12420 | D23: YYH-125 | E23: 白点净300ml | F23: White Spot Cleaner 300ml | G23: 0.71830986 | H23: 10 | I23: 7.18
A24: 15 | C24: 19768a | D24: YYH-207 | E24: 亚甲基蓝溶液 600ml | F24: Methylene blue solution 600ml | G24: 0.93 | H24: 8 | I24: 7.44
A25: 16 | C25: 02856a | D25: YYH-006 | E25: 杀菌/抑菌/速溶粉末2g/袋×10袋[1盒] | F25: Bactericidal/antibacterial/instant powder 2g/bag × 10 bags [1 box] | G25: 1.13 | H25: 6 | I25: 6.78
A26: 17 | C26: c2-1016-2 | D26: c2-1016 | E26: Yee意牌水族净氨系列活性益生菌760ml | F26: Yee Aquarium Cleansing Ammonia Series Active Probiotics 760ml | G26: 2.34 | H26: 10 | I26: 23.4
A27: 18 | C27: c2-1016-1a | D27: c2-1016 | E27: Yee意牌水族净氨系列活性益生菌400ml | F27: Yee Aquarium Cleansing Ammonia Series Active Probiotics 400ml | G27: 1.38 | H27: 5 | I27: 6.9
A28: 19 | C28: 02924 | D28: YYH-039 | E28: yee蓝色经典-除氯水质稳定剂535ml | F28: Yee Blue Classic-Chlorine Removal Water Stabilizer 535ml | G28: 0.72 | H28: 15 | I28: 10.8
A29: 20 | C29: 16940 | D29: YYH-173 | E29: 抗应激水质稳定剂 500ml 新风格 | F29: Anti-stress water stabilizer 500ml New style | G29: 0.91549296 | H29: 8 | I29: 7.32
A30: 21 | C30: C3-1010-3 | D30: C3-1010 | E30: 【氨氮测试剂】可测约60次/精准快速 | F30: 【Ammonia nitrogen tester】can test about 60 times/accurate and fast | G30: 2.87 | H30: 8 | I30: 22.96
A31: 22 | C31: C3-1010-1 | D31: C3-1010 | E31: 【亚硝酸盐测试剂】可测约100次/精准快速 | F31: 【Nitrite test kit】can test about 100 times/accurate and fast | G31: 2.87 | H31: 8 | I31: 22.96
A32: 23 | C32: C4-1123-1a | D32: C4-1123 | E32: 【新手级50条】9合1/桶装/带对比表 | F32: [Novice Level 50] 9-in-1/Bucket/With Comparison Chart | G32: 1.62 | H32: 10 | I32: 16.2
A33: 24 | C33: C2-1005-1 | D33: C2-1005 | E33: Yee意牌水族硝化菌+益生菌胶囊50粒 | F33: Yee Aquarium Nitrifying Bacteria + Probiotics Capsules 50 capsules | G33: 0.85 | H33: 12 | I33: 10.2
A34: 25 | C34: C2-1005-2 | D34: C2-1005 | E34: Yee意牌水族硝化菌+益生菌胶囊100粒 | F34: Yee Aquarium Nitrifying Bacteria + Probiotics Capsules 100 Capsules | G34: 1.27 | H34: 8 | I34: 10.16
A35: 26 | C35: 19429 | D35: YYH-189 | E35: 除藻剂 500ml 新风格 | F35: Algaecide 500ml New Style | G35: 0.91549296 | H35: 10 | I35: 9.15
A36: 27 | C36: 19939 | D36: YYH-216 | E36: 抗应激水质稳定剂 1000ml 新风格 | F36: Anti-stress water stabilizer 1000ml New style | G36: 1.1267606 | H36: 6 | I36: 6.76
A37: 28 | C37: 06834 | D37: YAN-804 | E37: 多维矿物盐500克 | F37: Multivitamin mineral salt 500g | G37: 0.2 | H37: 10 | I37: 2
A38: 29 | C38: 01831 | D38: YAN-915 | E38: 500G多维盐盒装YAN-915 | F38: 500G Multivitamin Salt Box YAN-915 | G38: 0.87 | H38: 5 | I38: 4.35
A39: 30 | C39: 02938a | D39: YYH-053 | E39: yee蓝色经典-亚甲基蓝溶液235ml | F39: Yee Blue Classic-Methylene Blue Solution 235ml | G39: 0.45 | H39: 10 | I39: 4.5
A40: 31 | C40: C4-1123-2a | D40: C4-1123 | E40: 【补充装】9合1/补充装/50条 | F40: 【Refill】9 in 1/Refill/50 pieces | G40: 1.06 | H40: 10 | I40: =G40*H40 -> 10.6
A41: 32 | C41: 1.5.1.7 | D41: YEE-3006 | E41: 50W纯钢加热棒 YSH-50 | F41: 50W pure steel heating rod YSH-50 | G41: 2.4788732 | H41: 8 | I41: =G41*H41 -> 19.830986
A42: 33 | C42: 1.5.1.8 | D42: YEE-3007 | E42: 100W纯钢加热棒 YSH-100 | F42: 100W pure steel heating rod YSH-100 | G42: 2.5633803 | H42: 8 | I42: =G42*H42 -> 20.507042
A43: 34 | C43: 1.5.1.9 | D43: YEE-3008 | E43: 200W纯钢加热棒 YSH-200 | F43: 200W pure steel heating rod YSH-200 | G43: 2.5774648 | H43: 8 | I43: =G43*H43 -> 20.619718
A44: 35 | C44: C4-1432-1 | D44: C4-1432 | E44: Yee意牌水族皓源石英加热棒 100W | F44: Yee brand aquarium quartz heating rod, 100W | G44: 9.76 | H44: 1 | I44: =G44*H44 -> 9.76
A45: 36 | C45: C4-1103-4 | D45: C4-1103 | E45: YEE黑武士加热棒 100W | F45: YEE Black Warrior Heater 100W | G45: 3.5211268 | H45: 5 | I45: =G45*H45 -> 17.605634
A46: 37 | C46: 07509 | D46: YFF-049 | E46: 水草泥肥力升级款细粒 1.5L | F46: Water grass mud fertility upgrade fine grain 1.5L | G46: 1.23 | H46: 18 | I46: 22.14 | J46: Nepal&Jiwo no stock
A47: 38 | C47: 07512 | D47: YFF-052 | E47: 水草泥肥力升级款 粗粒 3L | F47: Water grass mud fertility upgrade coarse grain 3L | G47: 2.39 | H47: 10 | I47: 23.9
A48: 39 | C48: 03326 | D48: YTZ-300 | E48: 小白单孔氧气泵3W（不可调）YTZ-300 | F48: Xiaobai single-hole oxygen pump 3W (non-adjustable) YTZ-300 | G48: 1.1690141 | H48: 3 | I48: 3.51
A49: 40 | C49: 07154 | D49: YGG-135 | E49: YEE 50mm 球形矿物质气泡扩散器 | F49: YEE 50mm Ball Mineral Bubble Diffuser | G49: 1.56 | H49: 15 | I49: 23.4
A50: 41 | C50: C5-1144-1a | D50: C5-1144 | E50: 加强版1.5米/加厚加长 | F50: Enhanced version 1.5 meters/thickened and lengthened | G50: 0.36619718 | H50: 10 | I50: 3.66
A51: 42 | C51: 1.8.3.2 | D51: YEE-3621 | E51: 【加厚气囊 经久耐用】1.7米 | F51: 【Thickened airbag for durability】1.7 meters | G51: 0.91549296 | H51: 10 | I51: 9.15
A52: 43 | C52: C4-1117-1 | D52: C4-1117 | E52: 高配30W 低水位 | F52: High configuration 30W low water level | G52: 8.2816901 | H52: 5 | I52: 41.41
A53: 44 | C53: C4-1008-1 | D53: C4-1008 | E53: 悬浮隔离盒大号 | F53: Large suspended isolation box | G53: 2.6760563 | H53: 8 | I53: 21.41
A54: 45 | C54: 02517 | D54: YSL-506 | E54: 大号气动孵化盒（双房） | F54: Large pneumatic incubator (double room) | G54: 0.99 | H54: 5 | I54: 4.95
A55: 46 | C55: 02771 | D55: YKL-018 | E55: 亚克力培养箱 20*10*10 | F55: Acrylic incubator 20*10*10 | G55: 2.86 | H55: 4 | I55: 11.44
A56: 47 | C56: 05617a | D56: YLL-087 | E56: （蓝色）新升级6D 过滤棉 50*40 两片装 | F56: (Blue) New upgraded 6D filter cotton 50*40 two pieces | G56: 3.0422535 | H56: 4 | I56: 12.17
A57: 48 | C57: 13343 | D57: PYD-200 | E57: 鱼缸除垢剂 200ml | F57: Fish tank descaling agent 200ml | G57: 0.76056338 | H57: 10 | I57: 7.61
A58: 49 | C58: 07116 | D58: YFF-042 | E58: 纳米培养环混合装 | F58: Nano Culture Ring Mixed Pack | G58: 1.31 | H58: 8 | I58: 10.48
A59: 50 | C59: 17699a | D59: YAA-009. | E59: 高能量培菌砖 | F59: High energy culture bricks | G59: 0.83 | H59: 5 | I59: 4.15
A60: 51 | C60: 11578 | D60: NYH-006 | E60: Nepall 3D曲奇滤材 500g | F60: 3D filter material | G60: 1.67 | H60: 6 | I60: 10.02
A61: 52 | C61: 71934 | D61: YLC-410 | E61: 十六合一滤材 2.5kg | F61: 16-in-1 filter material 2.5kg | G61: 2.6056338 | H61: 5 | I61: 13.03
A62: 53 | C62: 17831 | D62: YLC-409 | E62: 六合一滤材 500g | F62: Six-in-one filter material 500g | G62: 0.97183099 | H62: 5 | I62: 4.86
A63: 54 | C63: C4-1067-1 | D63: C4-1067 | E63: 3W 油膜处理器 | F63: 3W oil film processor | G63: 2.61 | H63: 4 | I63: 10.44
A64: 55 | C64: 00340 | D64: YEE-3606 | E64: 外贴电子温度计 | F64: External electronic thermometer | G64: 1.1 | H64: 4 | I64: 4.4
A65: 56 | C65: 08116 | D65: LED-318 | E65: yee三色可调 3.5W 双排广角灯27cm | F65: Yee three-color adjustable 3.5W double-row wide-angle light, 27cm | G65: 0 | H65: 4 | I65: 0 | J65: Free gift
A66: 57 | C66: 07140 | D66: CLS-107 | E66: 鱼缸磁力刷 大号 蓝色强磁 | F66: Aquarium magnetic cleaning brush, large size, blue, strong magnet. | G66: 0 | H66: 3 | I66: 0 | J66: Free gift
A67: 58 | C67: 1.15.60 | D67: YEE-3656 | E67: 16mm牛筋管1.0米 | F67: 1.0 meter of 16mm reinforced plastic tubing | G67: 0 | H67: 5 | I67: 0 | J67: Free gift
A68: 59 | C68: 06255 | D68: =VLOOKUP(C68,[1]水草缸!$A:$C,3,0) -> YXL-003 | E68: 400x230x250mm 5mm厚 | F68: 400x230x250mm 5mm thick | G68: 6.2816901 | H68: 2 | I68: =G68*H68 -> 12.56338
A69: 60 | C69: 05380 | D69: =VLOOKUP(C69,[1]水草缸!$A:$C,3,0) -> YKK-50 | E69: 500x270x300mm 5mm厚 | F69: 500x270x300mm 5mm thick | G69: 9.7323944 | H69: 2 | I69: =G69*H69 -> 19.464789
A70: 61 | C70: 05381 | D70: =VLOOKUP(C70,[1]水草缸!$A:$C,3,0) -> YKK-60 | E70: 600x300x350mm 5mm厚 | F70: 600x300x350mm 5mm thick | G70: 12.521127 | H70: 2 | I70: =G70*H70 -> 25.042254
A71: 62 | C71: 16932 | D71: =VLOOKUP(C71,[1]水草缸!$A:$C,3,0) -> YEE-1090 | E71: 35×35×35 6mm 厚 | F71: 35×35×35 6mm thick | G71: 8.5915493 | H71: 2 | I71: =G71*H71 -> 17.183099
A72: 63 | C72: 05662 | D72: =VLOOKUP(C72,[1]水草缸!$A:$C,3,0) -> YCG-40 | E72: 40X40X40cm 6mm厚 | F72: 40X40X40cm 6mm thick | G72: 11.549296 | H72: 2 | I72: =G72*H72 -> 23.098592
A73: 64 | C73: C5-1062-1 | D73: =VLOOKUP(C73,[1]水草缸!$A:$C,3,0) -> C5-1062 | E73: 60*40*40cm 8mm | F73: 60*40*40cm 8mm | G73: 18.169014 | H73: 2 | I73: =G73*H73 -> 36.338028
A74: 65 | C74: C5-1123-2 | D74: C5-1123 | E74: 裸缸侧虑溪流缸60*15*15cm 6mm送水泵 | F74: Bare side stream tank 60*15*15cm 6mm water pump | G74: 17.295775 | H74: 2 | I74: =G74*H74 -> 34.591549
A75: Products price | I75: =SUM(I10:I74) -> 848.50507
G76: Packaging fee | I76: 73
A77: Total | I77: =I75+I76 -> 921.50507
A78: Payment Term：100% payment before Delivery
